jinaai/__init__.py
jinaai/utils.py
jinaai/clients/BestBannerClient.py
jinaai/clients/ChatCatClient.py
jinaai/clients/HTTPClient.py
jinaai/clients/JinaChatClient.py
jinaai/clients/PromptPerfectClient.py
jinaai/clients/RationaleClient.py
jinaai/clients/SceneXClient.py
jinaai/clients/__init__.py
jinaai-0.2.10.dist-info/LICENSE
jinaai-0.2.10.dist-info/METADATA
jinaai-0.2.10.dist-info/WHEEL
jinaai-0.2.10.dist-info/top_level.txt
jinaai-0.2.10.dist-info/RECORD
