Metadata-Version: 2.1
Name: jinaai
Version: 0.2.10
Summary: Jina AI Python SDK
Home-page: https://github.com/jina-ai/jinaai-py.git
Author: Jina AI
Author-email: guillaume.roncari@jina.ai
License: UNKNOWN
Platform: UNKNOWN
License-File: LICENSE
